{"name":"Setup work environment","tagline":"","body":"# Setup work environment\r\n\r\nSystematics of experience...\r\n\r\nSetup minimal environment for use virtual machines on VirtualBox 5.0 and Vagrant 1.8.1 (plugins: cachier, hostmanager, bindfs)\r\n\r\n## Install\r\n\r\n    $ mkdir -p ~/bin/tools && cd $_\r\n    $ git clone https://github.com/ilyar/setup-work-environment.git --depth 1\r\n    $ ln $(pwd)/setup-work-environment/run.sh ~/setup-work-environment\r\n\r\n## Update\r\n\r\n    $ cd ~/bin/tools/setup-work-environment && git pull\r\n    \r\n# Usage for setup and update\r\n\r\n    $ setup-work-environment\r\n","google":"UA-47068199-1","note":"Don't delete this file! It's used internally to help with page regeneration."}